waffle/README.md
waffle/__init__.py
waffle/definitions.py
waffle/pacl.mplstyle
waffle/waffle.py
waffle/winkeltripel.py
waffle/reference_datasets/__init__.py
waffle/reference_datasets/sample_day_timeseries_ds.nc
waffle/reference_datasets/sample_spatial_ds.nc
waffle/reference_datasets/sample_timeseries_ds.nc
pacl_waffle-0.1.0.dist-info/LICENSE
pacl_waffle-0.1.0.dist-info/METADATA
pacl_waffle-0.1.0.dist-info/WHEEL
pacl_waffle-0.1.0.dist-info/top_level.txt
pacl_waffle-0.1.0.dist-info/RECORD
