Metadata-Version: 2.1
Name: pacl-waffle
Version: 0.1.0
Summary: Workflows and Automatic Fancy Figures for Large Ensembles (WAFFLE) is a toolkit tailored for use by researchers in and from the Persad Aero-Climate Lab (PACL).
Author-email: Cameron Cummins <cameron.cummins@utexas.edu>
License: MIT License
Project-URL: Homepage, https://github.com/AgentOxygen/WAFFLE
Project-URL: Issues, https://github.com/AgentOxygen/WAFFLE
Keywords: waffle,large ensembles,figure,matplotlib
Classifier: Programming Language :: Python :: 3
Classifier: License :: OSI Approved :: MIT License
Classifier: Operating System :: OS Independent
Requires-Python: >=3.12.3
License-File: LICENSE
Requires-Dist: xarray >=2024.3.0
Requires-Dist: numpy >=1.26.4
Requires-Dist: matplotlib >=3.8.4
Requires-Dist: cartopy
Requires-Dist: cftime
Requires-Dist: nc-time-axis
